{"description":"Imported from devices.esphome.io — see linked docs for community notes.","docs_url":"https://devices.esphome.io/devices/Earu-EA777/","esphome":{"board":"esp32dev","framework":"esp-idf","platform":"esp32","variant":"esp32"},"featured_bundles":[{"component_ids":["phase_a_voltage","phase_b_voltage","phase_c_voltage","phase_a_current","phase_b_current","phase_c_current","active_power","phase_a_active_power","phase_b_active_power","phase_c_active_power","reactive_power","phase_a_reactive_power","phase_b_reactive_power","phase_c_reactive_power","phase_a_power_factor","phase_b_power_factor","phase_c_power_factor","current_voltage_frequency","instrument_communication_address","communication_baud_rate","communication_data_format","current_total_active_energy","current_positive_total_active_energy","current_reverse_total_active_energy","current_total_reactive_energy","current_positive_total_reactive_energy","current_reverse_total_reactive_energy"],"id":"all_recommended","name":"Earu EA777 (full setup)"}],"featured_components":[{"component_id":"sensor.modbus_controller","fields":{"accuracy_decimals":{"value":1},"address":{"value":0},"id":{"value":"phase_a_voltage"},"name":{"value":"Phase A voltage"},"register_type":{"value":"read"},"unit_of_measurement":{"value":"V"},"value_type":{"value":"U_WORD"}},"id":"phase_a_voltage"},{"component_id":"sensor.modbus_controller","fields":{"accuracy_decimals":{"value":1},"address":{"value":1},"id":{"value":"phase_b_voltage"},"name":{"value":"Phase B voltage"},"register_type":{"value":"read"},"unit_of_measurement":{"value":"V"},"value_type":{"value":"U_WORD"}},"id":"phase_b_voltage"},{"component_id":"sensor.modbus_controller","fields":{"accuracy_decimals":{"value":1},"address":{"value":2},"id":{"value":"phase_c_voltage"},"name":{"value":"Phase C voltage"},"register_type":{"value":"read"},"unit_of_measurement":{"value":"V"},"value_type":{"value":"U_WORD"}},"id":"phase_c_voltage"},{"component_id":"sensor.modbus_controller","fields":{"accuracy_decimals":{"value":2},"address":{"value":3},"id":{"value":"phase_a_current"},"name":{"value":"Phase A current"},"register_type":{"value":"read"},"unit_of_measurement":{"value":"A"},"value_type":{"value":"U_WORD"}},"id":"phase_a_current"},{"component_id":"sensor.modbus_controller","fields":{"accuracy_decimals":{"value":2},"address":{"value":4},"id":{"value":"phase_b_current"},"name":{"value":"Phase B current"},"register_type":{"value":"read"},"unit_of_measurement":{"value":"A"},"value_type":{"value":"U_WORD"}},"id":"phase_b_current"},{"component_id":"sensor.modbus_controller","fields":{"accuracy_decimals":{"value":2},"address":{"value":5},"id":{"value":"phase_c_current"},"name":{"value":"Phase C current"},"register_type":{"value":"read"},"unit_of_measurement":{"value":"A"},"value_type":{"value":"U_WORD"}},"id":"phase_c_current"},{"component_id":"sensor.modbus_controller","fields":{"accuracy_decimals":{"value":2},"address":{"value":7},"id":{"value":"active_power"},"name":{"value":"Active power"},"register_type":{"value":"read"},"unit_of_measurement":{"value":"W"},"value_type":{"value":"U_WORD"}},"id":"active_power"},{"component_id":"sensor.modbus_controller","fields":{"accuracy_decimals":{"value":2},"address":{"value":8},"id":{"value":"phase_a_active_power"},"name":{"value":"Phase A active power"},"register_type":{"value":"read"},"unit_of_measurement":{"value":"W"},"value_type":{"value":"U_WORD"}},"id":"phase_a_active_power"},{"component_id":"sensor.modbus_controller","fields":{"accuracy_decimals":{"value":2},"address":{"value":9},"id":{"value":"phase_b_active_power"},"name":{"value":"Phase B active power"},"register_type":{"value":"read"},"unit_of_measurement":{"value":"W"},"value_type":{"value":"U_WORD"}},"id":"phase_b_active_power"},{"component_id":"sensor.modbus_controller","fields":{"accuracy_decimals":{"value":2},"address":{"value":10},"id":{"value":"phase_c_active_power"},"name":{"value":"Phase C active power"},"register_type":{"value":"read"},"unit_of_measurement":{"value":"W"},"value_type":{"value":"U_WORD"}},"id":"phase_c_active_power"},{"component_id":"sensor.modbus_controller","fields":{"accuracy_decimals":{"value":2},"address":{"value":11},"id":{"value":"reactive_power"},"name":{"value":"Reactive power"},"register_type":{"value":"read"},"unit_of_measurement":{"value":"W"},"value_type":{"value":"U_WORD"}},"id":"reactive_power"},{"component_id":"sensor.modbus_controller","fields":{"accuracy_decimals":{"value":2},"address":{"value":12},"id":{"value":"phase_a_reactive_power"},"name":{"value":"Phase A reactive power"},"register_type":{"value":"read"},"unit_of_measurement":{"value":"W"},"value_type":{"value":"U_WORD"}},"id":"phase_a_reactive_power"},{"component_id":"sensor.modbus_controller","fields":{"accuracy_decimals":{"value":2},"address":{"value":13},"id":{"value":"phase_b_reactive_power"},"name":{"value":"Phase B reactive power"},"register_type":{"value":"read"},"unit_of_measurement":{"value":"W"},"value_type":{"value":"U_WORD"}},"id":"phase_b_reactive_power"},{"component_id":"sensor.modbus_controller","fields":{"accuracy_decimals":{"value":2},"address":{"value":14},"id":{"value":"phase_c_reactive_power"},"name":{"value":"Phase C reactive power"},"register_type":{"value":"read"},"unit_of_measurement":{"value":"W"},"value_type":{"value":"U_WORD"}},"id":"phase_c_reactive_power"},{"component_id":"sensor.modbus_controller","fields":{"accuracy_decimals":{"value":3},"address":{"value":20},"id":{"value":"phase_a_power_factor"},"name":{"value":"Phase A power factor"},"register_type":{"value":"read"},"unit_of_measurement":{"value":"cos φ"},"value_type":{"value":"U_WORD"}},"id":"phase_a_power_factor"},{"component_id":"sensor.modbus_controller","fields":{"accuracy_decimals":{"value":3},"address":{"value":21},"id":{"value":"phase_b_power_factor"},"name":{"value":"Phase B power factor"},"register_type":{"value":"read"},"unit_of_measurement":{"value":"cos φ"},"value_type":{"value":"U_WORD"}},"id":"phase_b_power_factor"},{"component_id":"sensor.modbus_controller","fields":{"accuracy_decimals":{"value":3},"address":{"value":22},"id":{"value":"phase_c_power_factor"},"name":{"value":"Phase C power factor"},"register_type":{"value":"read"},"unit_of_measurement":{"value":"cos φ"},"value_type":{"value":"U_WORD"}},"id":"phase_c_power_factor"},{"component_id":"sensor.modbus_controller","fields":{"accuracy_decimals":{"value":2},"address":{"value":26},"id":{"value":"current_voltage_frequency"},"name":{"value":"Current voltage frequency"},"register_type":{"value":"read"},"unit_of_measurement":{"value":"Hz"},"value_type":{"value":"U_WORD"}},"id":"current_voltage_frequency"},{"component_id":"sensor.modbus_controller","fields":{"address":{"value":97},"id":{"value":"instrument_communication_address"},"name":{"value":"Instrument communication address"},"register_type":{"value":"read"},"value_type":{"value":"U_WORD"}},"id":"instrument_communication_address"},{"component_id":"sensor.modbus_controller","fields":{"address":{"value":98},"id":{"value":"communication_baud_rate"},"name":{"value":"Communication baud rate"},"register_type":{"value":"read"},"value_type":{"value":"U_WORD"}},"id":"communication_baud_rate"},{"component_id":"sensor.modbus_controller","fields":{"address":{"value":99},"id":{"value":"communication_data_format"},"name":{"value":"Communication data format"},"register_type":{"value":"read"},"value_type":{"value":"U_WORD"}},"id":"communication_data_format"},{"component_id":"sensor.modbus_controller","fields":{"accuracy_decimals":{"value":2},"address":{"value":29},"id":{"value":"current_total_active_energy"},"name":{"value":"Current total active energy"},"register_count":{"value":2},"register_type":{"value":"read"},"unit_of_measurement":{"value":"kWh"},"value_type":{"value":"U_DWORD"}},"id":"current_total_active_energy"},{"component_id":"sensor.modbus_controller","fields":{"accuracy_decimals":{"value":2},"address":{"value":39},"id":{"value":"current_positive_total_active_energy"},"name":{"value":"Current positive total active energy"},"register_count":{"value":2},"register_type":{"value":"read"},"unit_of_measurement":{"value":"kWh"},"value_type":{"value":"U_DWORD"}},"id":"current_positive_total_active_energy"},{"component_id":"sensor.modbus_controller","fields":{"accuracy_decimals":{"value":2},"address":{"value":49},"id":{"value":"current_reverse_total_active_energy"},"name":{"value":"Current reverse total active energy"},"register_count":{"value":2},"register_type":{"value":"read"},"unit_of_measurement":{"value":"kWh"},"value_type":{"value":"U_DWORD"}},"id":"current_reverse_total_active_energy"},{"component_id":"sensor.modbus_controller","fields":{"accuracy_decimals":{"value":2},"address":{"value":59},"id":{"value":"current_total_reactive_energy"},"name":{"value":"Current total reactive energy"},"register_count":{"value":2},"register_type":{"value":"read"},"unit_of_measurement":{"value":"kVArh"},"value_type":{"value":"U_DWORD"}},"id":"current_total_reactive_energy"},{"component_id":"sensor.modbus_controller","fields":{"accuracy_decimals":{"value":2},"address":{"value":69},"id":{"value":"current_positive_total_reactive_energy"},"name":{"value":"Current positive total reactive energy"},"register_count":{"value":2},"register_type":{"value":"read"},"unit_of_measurement":{"value":"kVArh"},"value_type":{"value":"U_DWORD"}},"id":"current_positive_total_reactive_energy"},{"component_id":"sensor.modbus_controller","fields":{"accuracy_decimals":{"value":2},"address":{"value":79},"id":{"value":"current_reverse_total_reactive_energy"},"name":{"value":"Current reverse total reactive energy"},"register_count":{"value":2},"register_type":{"value":"read"},"unit_of_measurement":{"value":"kVArh"},"value_type":{"value":"U_DWORD"}},"id":"current_reverse_total_reactive_energy"}],"full_config":true,"hardware":{"connectivity":["wifi","bluetooth"]},"id":"earu_ea777","images":["https://raw.githubusercontent.com/esphome/devices.esphome.io/main/src/docs/devices/Earu-EA777/esp32.png"],"manufacturer":"","name":"Earu EA777"}
