{"description":"Imported from devices.esphome.io — see linked docs for community notes.","docs_url":"https://devices.esphome.io/devices/GIRIER-Switch-4gang/","esphome":{"board":"generic-bk7231n-qfn32-tuya","platform":"bk72xx"},"featured_bundles":[{"component_ids":["binary_switch_1","binary_switch_2","binary_switch_3","binary_switch_4","switch_1","switch_2","switch_3","switch_4"],"id":"all_recommended","name":"GIRIER Switch 4 Gang ZS-TYT1-SM-41W-W (full setup)"}],"featured_components":[{"component_id":"binary_sensor.gpio","fields":{"id":{"value":"binary_switch_1"},"name":{"value":"binary_switch_1"},"pin":{"locked":true,"value":{"inverted":true,"mode":"INPUT_PULLUP","number":26}}},"id":"binary_switch_1","locked_pins":{"pin":26}},{"component_id":"binary_sensor.gpio","fields":{"id":{"value":"binary_switch_2"},"name":{"value":"binary_switch_2"},"pin":{"locked":true,"value":{"inverted":true,"mode":"INPUT_PULLUP","number":24}}},"id":"binary_switch_2","locked_pins":{"pin":24}},{"component_id":"binary_sensor.gpio","fields":{"id":{"value":"binary_switch_3"},"name":{"value":"binary_switch_3"},"pin":{"locked":true,"value":{"inverted":true,"mode":"INPUT_PULLUP","number":6}}},"id":"binary_switch_3","locked_pins":{"pin":6}},{"component_id":"binary_sensor.gpio","fields":{"id":{"value":"binary_switch_4"},"name":{"value":"binary_switch_4"},"pin":{"locked":true,"value":{"inverted":true,"mode":"INPUT_PULLUP","number":23}}},"id":"binary_switch_4","locked_pins":{"pin":23}},{"component_id":"switch.gpio","fields":{"id":{"value":"switch_1"},"name":{"value":"Relay 1"},"pin":{"locked":true,"value":14}},"id":"switch_1","locked_pins":{"pin":14}},{"component_id":"switch.gpio","fields":{"id":{"value":"switch_2"},"name":{"value":"Relay 2"},"pin":{"locked":true,"value":9}},"id":"switch_2","locked_pins":{"pin":9}},{"component_id":"switch.gpio","fields":{"id":{"value":"switch_3"},"name":{"value":"Relay 3"},"pin":{"locked":true,"value":8}},"id":"switch_3","locked_pins":{"pin":8}},{"component_id":"switch.gpio","fields":{"id":{"value":"switch_4"},"name":{"value":"Relay 4"},"pin":{"locked":true,"value":7}},"id":"switch_4","locked_pins":{"pin":7}}],"full_config":true,"hardware":{"connectivity":["wifi"]},"id":"girier_switch_4gang","images":["https://raw.githubusercontent.com/esphome/devices.esphome.io/main/src/docs/devices/GIRIER-Switch-4gang/front.jpg","https://raw.githubusercontent.com/esphome/devices.esphome.io/main/src/docs/devices/GIRIER-Switch-4gang/back.jpg","https://raw.githubusercontent.com/esphome/devices.esphome.io/main/src/docs/devices/GIRIER-Switch-4gang/box.jpg","https://raw.githubusercontent.com/esphome/devices.esphome.io/main/src/docs/devices/GIRIER-Switch-4gang/pcb.jpg"],"manufacturer":"","name":"GIRIER Switch 4 Gang ZS-TYT1-SM-41W-W","pins":[{"available":false,"gpio":6,"label":"GPIO6","occupied_by":"binary_switch_3"},{"available":false,"gpio":7,"label":"GPIO7","occupied_by":"Relay 4"},{"available":false,"gpio":8,"label":"GPIO8","occupied_by":"Relay 3"},{"available":false,"gpio":9,"label":"GPIO9","occupied_by":"Relay 2"},{"available":false,"gpio":14,"label":"GPIO14","occupied_by":"Relay 1"},{"available":false,"gpio":23,"label":"GPIO23","occupied_by":"binary_switch_4"},{"available":false,"gpio":24,"label":"GPIO24","occupied_by":"binary_switch_2"},{"available":false,"gpio":26,"label":"GPIO26","occupied_by":"binary_switch_1"}]}
