{"description":"Imported from devices.esphome.io — see linked docs for community notes.","docs_url":"https://devices.esphome.io/devices/KinCony-AS/","esphome":{"board":"esp32-s3-devkitc-1","framework":"esp-idf","platform":"esp32","variant":"esp32s3"},"featured_components":[{"component_id":"light.esp32_rmt_led_strip","fields":{"chipset":{"value":"ws2812"},"id":{"value":"led_ww"},"name":{"value":"on board light"},"num_leds":{"value":1},"pin":{"locked":true,"value":16},"rgb_order":{"value":"RGB"}},"id":"led_ww"}],"hardware":{"connectivity":["wifi","bluetooth"]},"id":"kincony_as","images":["https://raw.githubusercontent.com/esphome/devices.esphome.io/main/src/docs/devices/KinCony-AS/KinCony-AS-1.jpg","https://raw.githubusercontent.com/esphome/devices.esphome.io/main/src/docs/devices/KinCony-AS/KinCony-AS-5.jpg","https://raw.githubusercontent.com/esphome/devices.esphome.io/main/src/docs/devices/KinCony-AS/KinCony-AS-7.jpg"],"manufacturer":"","name":"KinCony-AS (ESP32 Voice Assistant)","pins":[{"available":false,"gpio":16,"label":"GPIO16","occupied_by":"on board light"}]}
