{"description":"Imported from devices.esphome.io — see linked docs for community notes.","docs_url":"https://devices.esphome.io/devices/KinCony-T32M/","esphome":{"board":"esp32-s3-devkitc-1","framework":"esp-idf","platform":"esp32","variant":"esp32s3"},"featured_components":[{"component_id":"binary_sensor.gpio","fields":{"id":{"value":"binary_sensor_gpio_1"},"name":{"value":"t32m-input01"},"pin":{"locked":true,"value":{"inverted":true,"mode":"INPUT","number":0,"pcf8574":"pcf8574_hub_in_1"}}},"id":"binary_sensor_gpio_1"},{"component_id":"binary_sensor.gpio","fields":{"id":{"value":"binary_sensor_gpio_2"},"name":{"value":"t32m-input02"},"pin":{"locked":true,"value":{"inverted":true,"mode":"INPUT","number":1,"pcf8574":"pcf8574_hub_in_1"}}},"id":"binary_sensor_gpio_2"},{"component_id":"binary_sensor.gpio","fields":{"id":{"value":"binary_sensor_gpio_3"},"name":{"value":"t32m-input03"},"pin":{"locked":true,"value":{"inverted":true,"mode":"INPUT","number":2,"pcf8574":"pcf8574_hub_in_1"}}},"id":"binary_sensor_gpio_3"},{"component_id":"binary_sensor.gpio","fields":{"id":{"value":"binary_sensor_gpio_4"},"name":{"value":"t32m-input04"},"pin":{"locked":true,"value":{"inverted":true,"mode":"INPUT","number":3,"pcf8574":"pcf8574_hub_in_1"}}},"id":"binary_sensor_gpio_4"},{"component_id":"binary_sensor.gpio","fields":{"id":{"value":"binary_sensor_gpio_5"},"name":{"value":"t32m-input05"},"pin":{"locked":true,"value":{"inverted":true,"mode":"INPUT","number":4,"pcf8574":"pcf8574_hub_in_1"}}},"id":"binary_sensor_gpio_5"},{"component_id":"binary_sensor.gpio","fields":{"id":{"value":"binary_sensor_gpio_6"},"name":{"value":"t32m-input06"},"pin":{"locked":true,"value":{"inverted":true,"mode":"INPUT","number":5,"pcf8574":"pcf8574_hub_in_1"}}},"id":"binary_sensor_gpio_6"},{"component_id":"binary_sensor.gpio","fields":{"id":{"value":"binary_sensor_gpio_7"},"name":{"value":"t32m-input07"},"pin":{"locked":true,"value":{"inverted":true,"mode":"INPUT","number":6,"pcf8574":"pcf8574_hub_in_1"}}},"id":"binary_sensor_gpio_7"},{"component_id":"binary_sensor.gpio","fields":{"id":{"value":"binary_sensor_gpio_8"},"name":{"value":"t32m-input08"},"pin":{"locked":true,"value":{"inverted":true,"mode":"INPUT","number":7,"pcf8574":"pcf8574_hub_in_1"}}},"id":"binary_sensor_gpio_8"},{"component_id":"binary_sensor.gpio","fields":{"id":{"value":"binary_sensor_gpio_9"},"name":{"value":"t32m-input09"},"pin":{"locked":true,"value":{"inverted":true,"mode":"INPUT","number":8,"pcf8574":"pcf8574_hub_in_1"}}},"id":"binary_sensor_gpio_9"},{"component_id":"binary_sensor.gpio","fields":{"id":{"value":"binary_sensor_gpio_10"},"name":{"value":"t32m-input10"},"pin":{"locked":true,"value":{"inverted":true,"mode":"INPUT","number":9,"pcf8574":"pcf8574_hub_in_1"}}},"id":"binary_sensor_gpio_10"},{"component_id":"binary_sensor.gpio","fields":{"id":{"value":"binary_sensor_gpio_11"},"name":{"value":"t32m-input11"},"pin":{"locked":true,"value":{"inverted":true,"mode":"INPUT","number":10,"pcf8574":"pcf8574_hub_in_1"}}},"id":"binary_sensor_gpio_11"},{"component_id":"binary_sensor.gpio","fields":{"id":{"value":"binary_sensor_gpio_12"},"name":{"value":"t32m-input12"},"pin":{"locked":true,"value":{"inverted":true,"mode":"INPUT","number":11,"pcf8574":"pcf8574_hub_in_1"}}},"id":"binary_sensor_gpio_12"},{"component_id":"binary_sensor.gpio","fields":{"id":{"value":"binary_sensor_gpio_13"},"name":{"value":"t32m-input13"},"pin":{"locked":true,"value":{"inverted":true,"mode":"INPUT","number":12,"pcf8574":"pcf8574_hub_in_1"}}},"id":"binary_sensor_gpio_13"},{"component_id":"binary_sensor.gpio","fields":{"id":{"value":"binary_sensor_gpio_14"},"name":{"value":"t32m-input14"},"pin":{"locked":true,"value":{"inverted":true,"mode":"INPUT","number":13,"pcf8574":"pcf8574_hub_in_1"}}},"id":"binary_sensor_gpio_14"},{"component_id":"binary_sensor.gpio","fields":{"id":{"value":"binary_sensor_gpio_15"},"name":{"value":"t32m-input15"},"pin":{"locked":true,"value":{"inverted":true,"mode":"INPUT","number":14,"pcf8574":"pcf8574_hub_in_1"}}},"id":"binary_sensor_gpio_15"},{"component_id":"binary_sensor.gpio","fields":{"id":{"value":"binary_sensor_gpio_16"},"name":{"value":"t32m-input16"},"pin":{"locked":true,"value":{"inverted":true,"mode":"INPUT","number":15,"pcf8574":"pcf8574_hub_in_1"}}},"id":"binary_sensor_gpio_16"},{"component_id":"binary_sensor.gpio","fields":{"id":{"value":"binary_sensor_gpio_17"},"name":{"value":"t32m-input17"},"pin":{"locked":true,"value":{"inverted":true,"mode":"INPUT","number":0,"pcf8574":"pcf8574_hub_in_2"}}},"id":"binary_sensor_gpio_17"},{"component_id":"binary_sensor.gpio","fields":{"id":{"value":"binary_sensor_gpio_18"},"name":{"value":"t32m-input18"},"pin":{"locked":true,"value":{"inverted":true,"mode":"INPUT","number":1,"pcf8574":"pcf8574_hub_in_2"}}},"id":"binary_sensor_gpio_18"},{"component_id":"binary_sensor.gpio","fields":{"id":{"value":"binary_sensor_gpio_19"},"name":{"value":"t32m-input19"},"pin":{"locked":true,"value":{"inverted":true,"mode":"INPUT","number":2,"pcf8574":"pcf8574_hub_in_2"}}},"id":"binary_sensor_gpio_19"},{"component_id":"binary_sensor.gpio","fields":{"id":{"value":"binary_sensor_gpio_20"},"name":{"value":"t32m-input20"},"pin":{"locked":true,"value":{"inverted":true,"mode":"INPUT","number":3,"pcf8574":"pcf8574_hub_in_2"}}},"id":"binary_sensor_gpio_20"},{"component_id":"binary_sensor.gpio","fields":{"id":{"value":"binary_sensor_gpio_21"},"name":{"value":"t32m-input21"},"pin":{"locked":true,"value":{"inverted":true,"mode":"INPUT","number":4,"pcf8574":"pcf8574_hub_in_2"}}},"id":"binary_sensor_gpio_21"},{"component_id":"binary_sensor.gpio","fields":{"id":{"value":"binary_sensor_gpio_22"},"name":{"value":"t32m-input22"},"pin":{"locked":true,"value":{"inverted":true,"mode":"INPUT","number":5,"pcf8574":"pcf8574_hub_in_2"}}},"id":"binary_sensor_gpio_22"},{"component_id":"binary_sensor.gpio","fields":{"id":{"value":"binary_sensor_gpio_23"},"name":{"value":"t32m-input23"},"pin":{"locked":true,"value":{"inverted":true,"mode":"INPUT","number":6,"pcf8574":"pcf8574_hub_in_2"}}},"id":"binary_sensor_gpio_23"},{"component_id":"binary_sensor.gpio","fields":{"id":{"value":"binary_sensor_gpio_24"},"name":{"value":"t32m-input24"},"pin":{"locked":true,"value":{"inverted":true,"mode":"INPUT","number":7,"pcf8574":"pcf8574_hub_in_2"}}},"id":"binary_sensor_gpio_24"},{"component_id":"binary_sensor.gpio","fields":{"id":{"value":"binary_sensor_gpio_25"},"name":{"value":"t32m-input25"},"pin":{"locked":true,"value":{"inverted":true,"mode":"INPUT","number":8,"pcf8574":"pcf8574_hub_in_2"}}},"id":"binary_sensor_gpio_25"},{"component_id":"binary_sensor.gpio","fields":{"id":{"value":"binary_sensor_gpio_26"},"name":{"value":"t32m-input26"},"pin":{"locked":true,"value":{"inverted":true,"mode":"INPUT","number":9,"pcf8574":"pcf8574_hub_in_2"}}},"id":"binary_sensor_gpio_26"},{"component_id":"binary_sensor.gpio","fields":{"id":{"value":"binary_sensor_gpio_27"},"name":{"value":"t32m-input27"},"pin":{"locked":true,"value":{"inverted":true,"mode":"INPUT","number":10,"pcf8574":"pcf8574_hub_in_2"}}},"id":"binary_sensor_gpio_27"},{"component_id":"binary_sensor.gpio","fields":{"id":{"value":"binary_sensor_gpio_28"},"name":{"value":"t32m-input28"},"pin":{"locked":true,"value":{"inverted":true,"mode":"INPUT","number":11,"pcf8574":"pcf8574_hub_in_2"}}},"id":"binary_sensor_gpio_28"},{"component_id":"binary_sensor.gpio","fields":{"id":{"value":"binary_sensor_gpio_29"},"name":{"value":"t32m-input29"},"pin":{"locked":true,"value":{"inverted":true,"mode":"INPUT","number":12,"pcf8574":"pcf8574_hub_in_2"}}},"id":"binary_sensor_gpio_29"},{"component_id":"binary_sensor.gpio","fields":{"id":{"value":"binary_sensor_gpio_30"},"name":{"value":"t32m-input30"},"pin":{"locked":true,"value":{"inverted":true,"mode":"INPUT","number":13,"pcf8574":"pcf8574_hub_in_2"}}},"id":"binary_sensor_gpio_30"},{"component_id":"binary_sensor.gpio","fields":{"id":{"value":"binary_sensor_gpio_31"},"name":{"value":"t32m-input31"},"pin":{"locked":true,"value":{"inverted":true,"mode":"INPUT","number":14,"pcf8574":"pcf8574_hub_in_2"}}},"id":"binary_sensor_gpio_31"},{"component_id":"binary_sensor.gpio","fields":{"id":{"value":"binary_sensor_gpio_32"},"name":{"value":"t32m-input32"},"pin":{"locked":true,"value":{"inverted":true,"mode":"INPUT","number":15,"pcf8574":"pcf8574_hub_in_2"}}},"id":"binary_sensor_gpio_32"},{"component_id":"binary_sensor.gpio","fields":{"id":{"value":"binary_sensor_gpio_33"},"name":{"value":"t32m-W1-io15"},"pin":{"locked":true,"value":{"inverted":true,"number":15}}},"id":"binary_sensor_gpio_33"},{"component_id":"binary_sensor.gpio","fields":{"id":{"value":"binary_sensor_gpio_34"},"name":{"value":"t32m-W1-io16"},"pin":{"locked":true,"value":{"inverted":false,"number":16}}},"id":"binary_sensor_gpio_34"},{"component_id":"binary_sensor.gpio","fields":{"id":{"value":"binary_sensor_gpio_35"},"name":{"value":"t32m-W1-io17"},"pin":{"locked":true,"value":{"inverted":false,"number":17}}},"id":"binary_sensor_gpio_35"},{"component_id":"binary_sensor.gpio","fields":{"id":{"value":"binary_sensor_gpio_36"},"name":{"value":"t32m-W1-io18"},"pin":{"locked":true,"value":{"inverted":false,"number":18}}},"id":"binary_sensor_gpio_36"},{"component_id":"binary_sensor.gpio","fields":{"id":{"value":"binary_sensor_gpio_37"},"name":{"value":"t32m-io0"},"pin":{"locked":true,"value":{"inverted":false,"number":0}}},"id":"binary_sensor_gpio_37"},{"component_id":"binary_sensor.gpio","fields":{"id":{"value":"binary_sensor_gpio_38"},"name":{"value":"t32m-io8"},"pin":{"locked":true,"value":{"inverted":false,"number":8}}},"id":"binary_sensor_gpio_38"},{"component_id":"binary_sensor.gpio","fields":{"id":{"value":"binary_sensor_gpio_39"},"name":{"value":"t32m-io9"},"pin":{"locked":true,"value":{"inverted":false,"number":9}}},"id":"binary_sensor_gpio_39"},{"component_id":"binary_sensor.gpio","fields":{"id":{"value":"binary_sensor_gpio_40"},"name":{"value":"t32m-io10"},"pin":{"locked":true,"value":{"inverted":false,"number":10}}},"id":"binary_sensor_gpio_40"},{"component_id":"sensor.adc","fields":{"attenuation":{"value":"11db"},"id":{"value":"sensor_adc_1"},"name":{"value":"t32m A1 Voltage"},"pin":{"locked":true,"value":7},"update_interval":{"value":"5s"}},"id":"sensor_adc_1"},{"component_id":"sensor.adc","fields":{"attenuation":{"value":"11db"},"id":{"value":"sensor_adc_2"},"name":{"value":"t32m A2 Voltage"},"pin":{"locked":true,"value":6},"update_interval":{"value":"5s"}},"id":"sensor_adc_2"},{"component_id":"sensor.adc","fields":{"attenuation":{"value":"11db"},"id":{"value":"sensor_adc_3"},"name":{"value":"t32m A3 Current"},"pin":{"locked":true,"value":5},"unit_of_measurement":{"value":"mA"},"update_interval":{"value":"5s"}},"id":"sensor_adc_3"},{"component_id":"sensor.adc","fields":{"attenuation":{"value":"11db"},"id":{"value":"sensor_adc_4"},"name":{"value":"t32m A4 Current"},"pin":{"locked":true,"value":4},"unit_of_measurement":{"value":"mA"},"update_interval":{"value":"5s"}},"id":"sensor_adc_4"},{"component_id":"switch.gpio","fields":{"id":{"value":"t32m_output01"},"name":{"value":"t32m-output01"},"pin":{"locked":true,"value":{"inverted":true,"mode":"OUTPUT","number":0,"pcf8574":"pcf8574_hub_out_1"}}},"id":"t32m_output01"},{"component_id":"switch.gpio","fields":{"id":{"value":"t32m_output02"},"name":{"value":"t32m-output02"},"pin":{"locked":true,"value":{"inverted":true,"mode":"OUTPUT","number":1,"pcf8574":"pcf8574_hub_out_1"}}},"id":"t32m_output02"},{"component_id":"switch.gpio","fields":{"id":{"value":"t32m_output03"},"name":{"value":"t32m-output03"},"pin":{"locked":true,"value":{"inverted":true,"mode":"OUTPUT","number":2,"pcf8574":"pcf8574_hub_out_1"}}},"id":"t32m_output03"},{"component_id":"switch.gpio","fields":{"id":{"value":"t32m_output04"},"name":{"value":"t32m-output04"},"pin":{"locked":true,"value":{"inverted":true,"mode":"OUTPUT","number":3,"pcf8574":"pcf8574_hub_out_1"}}},"id":"t32m_output04"},{"component_id":"switch.gpio","fields":{"id":{"value":"t32m_output05"},"name":{"value":"t32m-output05"},"pin":{"locked":true,"value":{"inverted":true,"mode":"OUTPUT","number":4,"pcf8574":"pcf8574_hub_out_1"}}},"id":"t32m_output05"},{"component_id":"switch.gpio","fields":{"id":{"value":"t32m_output06"},"name":{"value":"t32m-output06"},"pin":{"locked":true,"value":{"inverted":true,"mode":"OUTPUT","number":5,"pcf8574":"pcf8574_hub_out_1"}}},"id":"t32m_output06"},{"component_id":"switch.gpio","fields":{"id":{"value":"t32m_output07"},"name":{"value":"t32m-output07"},"pin":{"locked":true,"value":{"inverted":true,"mode":"OUTPUT","number":6,"pcf8574":"pcf8574_hub_out_1"}}},"id":"t32m_output07"},{"component_id":"switch.gpio","fields":{"id":{"value":"t32m_output08"},"name":{"value":"t32m-output08"},"pin":{"locked":true,"value":{"inverted":true,"mode":"OUTPUT","number":7,"pcf8574":"pcf8574_hub_out_1"}}},"id":"t32m_output08"},{"component_id":"switch.gpio","fields":{"id":{"value":"t32m_output09"},"name":{"value":"t32m-output09"},"pin":{"locked":true,"value":{"inverted":true,"mode":"OUTPUT","number":8,"pcf8574":"pcf8574_hub_out_1"}}},"id":"t32m_output09"},{"component_id":"switch.gpio","fields":{"id":{"value":"t32m_output10"},"name":{"value":"t32m-output10"},"pin":{"locked":true,"value":{"inverted":true,"mode":"OUTPUT","number":9,"pcf8574":"pcf8574_hub_out_1"}}},"id":"t32m_output10"},{"component_id":"switch.gpio","fields":{"id":{"value":"t32m_output11"},"name":{"value":"t32m-output11"},"pin":{"locked":true,"value":{"inverted":true,"mode":"OUTPUT","number":10,"pcf8574":"pcf8574_hub_out_1"}}},"id":"t32m_output11"},{"component_id":"switch.gpio","fields":{"id":{"value":"t32m_output12"},"name":{"value":"t32m-output12"},"pin":{"locked":true,"value":{"inverted":true,"mode":"OUTPUT","number":11,"pcf8574":"pcf8574_hub_out_1"}}},"id":"t32m_output12"},{"component_id":"switch.gpio","fields":{"id":{"value":"t32m_output13"},"name":{"value":"t32m-output13"},"pin":{"locked":true,"value":{"inverted":true,"mode":"OUTPUT","number":12,"pcf8574":"pcf8574_hub_out_1"}}},"id":"t32m_output13"},{"component_id":"switch.gpio","fields":{"id":{"value":"t32m_output14"},"name":{"value":"t32m-output14"},"pin":{"locked":true,"value":{"inverted":true,"mode":"OUTPUT","number":13,"pcf8574":"pcf8574_hub_out_1"}}},"id":"t32m_output14"},{"component_id":"switch.gpio","fields":{"id":{"value":"t32m_output15"},"name":{"value":"t32m-output15"},"pin":{"locked":true,"value":{"inverted":true,"mode":"OUTPUT","number":14,"pcf8574":"pcf8574_hub_out_1"}}},"id":"t32m_output15"},{"component_id":"switch.gpio","fields":{"id":{"value":"t32m_output16"},"name":{"value":"t32m-output16"},"pin":{"locked":true,"value":{"inverted":true,"mode":"OUTPUT","number":15,"pcf8574":"pcf8574_hub_out_1"}}},"id":"t32m_output16"},{"component_id":"switch.gpio","fields":{"id":{"value":"t32m_output17"},"name":{"value":"t32m-output17"},"pin":{"locked":true,"value":{"inverted":true,"mode":"OUTPUT","number":0,"pcf8574":"pcf8574_hub_out_2"}}},"id":"t32m_output17"},{"component_id":"switch.gpio","fields":{"id":{"value":"t32m_output18"},"name":{"value":"t32m-output18"},"pin":{"locked":true,"value":{"inverted":true,"mode":"OUTPUT","number":1,"pcf8574":"pcf8574_hub_out_2"}}},"id":"t32m_output18"},{"component_id":"switch.gpio","fields":{"id":{"value":"t32m_output19"},"name":{"value":"t32m-output19"},"pin":{"locked":true,"value":{"inverted":true,"mode":"OUTPUT","number":2,"pcf8574":"pcf8574_hub_out_2"}}},"id":"t32m_output19"},{"component_id":"switch.gpio","fields":{"id":{"value":"t32m_output20"},"name":{"value":"t32m-output20"},"pin":{"locked":true,"value":{"inverted":true,"mode":"OUTPUT","number":3,"pcf8574":"pcf8574_hub_out_2"}}},"id":"t32m_output20"},{"component_id":"switch.gpio","fields":{"id":{"value":"t32m_output21"},"name":{"value":"t32m-output21"},"pin":{"locked":true,"value":{"inverted":true,"mode":"OUTPUT","number":4,"pcf8574":"pcf8574_hub_out_2"}}},"id":"t32m_output21"},{"component_id":"switch.gpio","fields":{"id":{"value":"t32m_output22"},"name":{"value":"t32m-output22"},"pin":{"locked":true,"value":{"inverted":true,"mode":"OUTPUT","number":5,"pcf8574":"pcf8574_hub_out_2"}}},"id":"t32m_output22"},{"component_id":"switch.gpio","fields":{"id":{"value":"t32m_output23"},"name":{"value":"t32m-output23"},"pin":{"locked":true,"value":{"inverted":true,"mode":"OUTPUT","number":6,"pcf8574":"pcf8574_hub_out_2"}}},"id":"t32m_output23"},{"component_id":"switch.gpio","fields":{"id":{"value":"t32m_output24"},"name":{"value":"t32m-output24"},"pin":{"locked":true,"value":{"inverted":true,"mode":"OUTPUT","number":7,"pcf8574":"pcf8574_hub_out_2"}}},"id":"t32m_output24"},{"component_id":"switch.gpio","fields":{"id":{"value":"t32m_output25"},"name":{"value":"t32m-output25"},"pin":{"locked":true,"value":{"inverted":true,"mode":"OUTPUT","number":8,"pcf8574":"pcf8574_hub_out_2"}}},"id":"t32m_output25"},{"component_id":"switch.gpio","fields":{"id":{"value":"t32m_output26"},"name":{"value":"t32m-output26"},"pin":{"locked":true,"value":{"inverted":true,"mode":"OUTPUT","number":9,"pcf8574":"pcf8574_hub_out_2"}}},"id":"t32m_output26"},{"component_id":"switch.gpio","fields":{"id":{"value":"t32m_output27"},"name":{"value":"t32m-output27"},"pin":{"locked":true,"value":{"inverted":true,"mode":"OUTPUT","number":10,"pcf8574":"pcf8574_hub_out_2"}}},"id":"t32m_output27"},{"component_id":"switch.gpio","fields":{"id":{"value":"t32m_output28"},"name":{"value":"t32m-output28"},"pin":{"locked":true,"value":{"inverted":true,"mode":"OUTPUT","number":11,"pcf8574":"pcf8574_hub_out_2"}}},"id":"t32m_output28"},{"component_id":"switch.gpio","fields":{"id":{"value":"t32m_output29"},"name":{"value":"t32m-output29"},"pin":{"locked":true,"value":{"inverted":true,"mode":"OUTPUT","number":12,"pcf8574":"pcf8574_hub_out_2"}}},"id":"t32m_output29"},{"component_id":"switch.gpio","fields":{"id":{"value":"t32m_output30"},"name":{"value":"t32m-output30"},"pin":{"locked":true,"value":{"inverted":true,"mode":"OUTPUT","number":13,"pcf8574":"pcf8574_hub_out_2"}}},"id":"t32m_output30"},{"component_id":"switch.gpio","fields":{"id":{"value":"t32m_output31"},"name":{"value":"t32m-output31"},"pin":{"locked":true,"value":{"inverted":true,"mode":"OUTPUT","number":14,"pcf8574":"pcf8574_hub_out_2"}}},"id":"t32m_output31"},{"component_id":"switch.gpio","fields":{"id":{"value":"t32m_output32"},"name":{"value":"t32m-output32"},"pin":{"locked":true,"value":{"inverted":true,"mode":"OUTPUT","number":15,"pcf8574":"pcf8574_hub_out_2"}}},"id":"t32m_output32"}],"hardware":{"connectivity":["wifi","bluetooth"]},"id":"kincony_t32m","images":["https://raw.githubusercontent.com/esphome/devices.esphome.io/main/src/docs/devices/KinCony-T32M/T32M-1.jpg"],"manufacturer":"","name":"KinCony-T32M (ESP32-S3 32CH Mosfet board)","pins":[{"available":false,"gpio":0,"label":"GPIO0","occupied_by":"t32m-output17"},{"available":false,"gpio":1,"label":"GPIO1","occupied_by":"t32m-output18"},{"available":false,"gpio":2,"label":"GPIO2","occupied_by":"t32m-output19"},{"available":false,"gpio":3,"label":"GPIO3","occupied_by":"t32m-output20"},{"available":false,"gpio":4,"label":"GPIO4","occupied_by":"t32m-output21"},{"available":false,"gpio":5,"label":"GPIO5","occupied_by":"t32m-output22"},{"available":false,"gpio":6,"label":"GPIO6","occupied_by":"t32m-output23"},{"available":false,"gpio":7,"label":"GPIO7","occupied_by":"t32m-output24"},{"available":false,"gpio":8,"label":"GPIO8","occupied_by":"t32m-output25"},{"available":false,"gpio":9,"label":"GPIO9","occupied_by":"t32m-output26"},{"available":false,"gpio":10,"label":"GPIO10","occupied_by":"t32m-output27"},{"available":false,"gpio":11,"label":"GPIO11","occupied_by":"t32m-output28"},{"available":false,"gpio":12,"label":"GPIO12","occupied_by":"t32m-output29"},{"available":false,"gpio":13,"label":"GPIO13","occupied_by":"t32m-output30"},{"available":false,"gpio":14,"label":"GPIO14","occupied_by":"t32m-output31"},{"available":false,"gpio":15,"label":"GPIO15","occupied_by":"t32m-output32"},{"available":false,"gpio":16,"label":"GPIO16","occupied_by":"t32m-W1-io16"},{"available":false,"gpio":17,"label":"GPIO17","occupied_by":"t32m-W1-io17"},{"available":false,"gpio":18,"label":"GPIO18","occupied_by":"t32m-W1-io18"}],"tags":["relay"]}
