{"description":"Imported from devices.esphome.io — see linked docs for community notes.","docs_url":"https://devices.esphome.io/devices/Shelly-The-Pill/","esphome":{"board":"esp32-c3-devkitm-1","framework":"esp-idf","platform":"esp32"},"featured_components":[{"component_id":"binary_sensor.gpio","fields":{"id":{"value":"binary_sensor_gpio_1"},"name":{"value":"Button"},"pin":{"locked":true,"value":{"inverted":true,"mode":"INPUT_PULLUP","number":10}}},"id":"binary_sensor_gpio_1"},{"component_id":"sensor.dallas_temp","fields":{"id":{"value":"sensor_dallas_temp_1"},"name":{"value":"Temperature"},"update_interval":{"value":"30s"}},"id":"sensor_dallas_temp_1"},{"component_id":"sensor.wifi_signal","fields":{"id":{"value":"sensor_wifi_signal_1"},"name":{"value":"WiFi Signal"},"update_interval":{"value":"60s"}},"id":"sensor_wifi_signal_1"},{"component_id":"switch.gpio","fields":{"id":{"value":"output_1"},"name":{"value":"Output 1"},"pin":{"locked":true,"value":3},"restore_mode":{"value":"RESTORE_DEFAULT_OFF"}},"id":"output_1"},{"component_id":"switch.gpio","fields":{"id":{"value":"output_2"},"name":{"value":"Output 2"},"pin":{"locked":true,"value":6},"restore_mode":{"value":"RESTORE_DEFAULT_OFF"}},"id":"output_2"}],"hardware":{"connectivity":["wifi","bluetooth"]},"id":"shelly_the_pill","images":["https://raw.githubusercontent.com/esphome/esphome-devices/main/src/docs/devices/Shelly-The-Pill/shelly-pill.png","https://raw.githubusercontent.com/esphome/esphome-devices/main/src/docs/devices/Shelly-The-Pill/PCB_Top.png"],"manufacturer":"","name":"Shelly Pill","pins":[{"available":false,"gpio":3,"label":"GPIO3","occupied_by":"Output 1"},{"available":false,"gpio":6,"label":"GPIO6","occupied_by":"Output 2"},{"available":false,"gpio":10,"label":"GPIO10","occupied_by":"Button"}],"tags":["shelly"]}
