{"id":"adalight","name":"Light → Adalight","config_entries":[{"key":"name","type":"string","label":"Name","default_value":"Adalight","display_format":null},{"key":"uart_id","type":"id","label":"UART ID","display_format":null,"references_component":"uart"}],"applies_to":["light.beken_spi_led_strip","light.esp32_rmt_led_strip","light.fastled_clockless","light.fastled_spi","light.m5stack_8angle","light.neopixelbus","light.partition","light.rp2040_pio_led_strip","light.spi_led_strip"],"value_type":null}
